[{"business_status": "OPERATIONAL", "geometry": {"location": {"lat": 40.1926519, "lng": -3.8037271}, "viewport": {"northeast": {"lat": 40.19407483029149, "lng": -3.802323619708497}, "southwest": {"lat": 40.19137686970849, "lng": -3.805021580291502}}}, "icon": "https://maps.gstatic.com/mapfiles/place_api/icons/v1/png_71/parking-71.png", "icon_background_color": "#7B9EB0", "icon_mask_base_uri": "https://maps.gstatic.com/mapfiles/place_api/icons/v2/parking_pinlet", "name": "Aparcamiento Clientes Supermercado Mercadona", "place_id": "ChIJwbPgqef1QQ0RKovBZDawhLQ", "plus_code": {"compound_code": "55VW+3G Torrejón de la Calzada, Spain", "global_code": "8CGR55VW+3G"}, "rating": 5, "reference": "ChIJwbPgqef1QQ0RKovBZDawhLQ", "scope": "GOOGLE", "types": ["parking", "point_of_interest", "establishment"], "user_ratings_total": 1, "vicinity": "Calle Real, 74, Torrejón de la Calzada"}, {"business_status": "OPERATIONAL", "geometry": {"location": {"lat": 40.192698, "lng": -3.804084799999999}, "viewport": {"northeast": {"lat": 40.1940274802915, "lng": -3.802690219708497}, "southwest": {"lat": 40.1913295197085, "lng": -3.805388180291501}}}, "icon": "https://maps.gstatic.com/mapfiles/place_api/icons/v1/png_71/parking-71.png", "icon_background_color": "#7B9EB0", "icon_mask_base_uri": "https://maps.gstatic.com/mapfiles/place_api/icons/v2/parking_pinlet", "name": "Aparcamiento Discapacitados", "place_id": "ChIJsSlo_aT1QQ0RJmqdnAJCemw", "plus_code": {"compound_code": "55VW+39 Torrejón de la Calzada, Spain", "global_code": "8CGR55VW+39"}, "rating": 1, "reference": "ChIJsSlo_aT1QQ0RJmqdnAJCemw", "scope": "GOOGLE", "types": ["parking", "point_of_interest", "establishment"], "user_ratings_total": 1, "vicinity": "Calle Real, 74, Torrejón de la Calzada"}, {"business_status": "OPERATIONAL", "geometry": {"location": {"lat": 40.2013583, "lng": -3.799508}, "viewport": {"northeast": {"lat": 40.2027631302915, "lng": -3.798242869708497}, "southwest": {"lat": 40.2000651697085, "lng": -3.800940830291502}}}, "icon": "https://maps.gstatic.com/mapfiles/place_api/icons/v1/png_71/parking-71.png", "icon_background_color": "#7B9EB0", "icon_mask_base_uri": "https://maps.gstatic.com/mapfiles/place_api/icons/v2/parking_pinlet", "name": "Aparcamiento de movilidad reducida", "place_id": "ChIJb47iRwD1QQ0Rk6IRpfnLvI4", "plus_code": {"compound_code": "6622+G5 Torrejón de la Calzada, Spain", "global_code": "8CGR6622+G5"}, "reference": "ChIJb47iRwD1QQ0Rk6IRpfnLvI4", "scope": "GOOGLE", "types": ["parking", "point_of_interest", "establishment"], "vicinity": "Torrejón de la Calzada"}]