[{"business_status": "OPERATIONAL", "geometry": {"location": {"lat": 40.81407919999999, "lng": -3.7589292}, "viewport": {"northeast": {"lat": 40.8153431302915, "lng": -3.757657769708497}, "southwest": {"lat": 40.8126451697085, "lng": -3.760355730291502}}}, "icon": "https://maps.gstatic.com/mapfiles/place_api/icons/v1/png_71/civic_building-71.png", "icon_background_color": "#7B9EB0", "icon_mask_base_uri": "https://maps.gstatic.com/mapfiles/place_api/icons/v2/civic-bldg_pinlet", "international_phone_number": "+34 918 44 31 10", "name": "Guardia Civil de Miraflores de la Sierra", "opening_hours": {"open_now": false}, "place_id": "ChIJ9eu_RyFiQQ0RaT7VidTeiPQ", "plus_code": {"compound_code": "R67R+JC Miraflores de la Sierra, Spain", "global_code": "8CGRR67R+JC"}, "rating": 3.7, "reference": "ChIJ9eu_RyFiQQ0RaT7VidTeiPQ", "scope": "GOOGLE", "types": ["police", "point_of_interest", "establishment"], "user_ratings_total": 6, "vicinity": "Carretera de Bustarviejo, 35, Miraflores de la Sierra"}, {"business_status": "OPERATIONAL", "geometry": {"location": {"lat": 40.75291469999999, "lng": -3.7841505}, "viewport": {"northeast": {"lat": 40.7541713302915, "lng": -3.782817419708498}, "southwest": {"lat": 40.7514733697085, "lng": -3.785515380291503}}}, "icon": "https://maps.gstatic.com/mapfiles/place_api/icons/v1/png_71/civic_building-71.png", "icon_background_color": "#7B9EB0", "icon_mask_base_uri": "https://maps.gstatic.com/mapfiles/place_api/icons/v2/civic-bldg_pinlet", "international_phone_number": "+34 918 47 70 47", "name": "Guardia Civil de Soto del Real", "opening_hours": {"open_now": false}, "place_id": "ChIJcZB7gCBjQQ0RVx8VgyGGswE", "plus_code": {"compound_code": "Q638+58 Soto del Real, Spain", "global_code": "8CGRQ638+58"}, "rating": 3.2, "reference": "ChIJcZB7gCBjQQ0RVx8VgyGGswE", "scope": "GOOGLE", "types": ["police", "point_of_interest", "establishment"], "user_ratings_total": 9, "vicinity": "Calle la Orden, 6, Soto del Real"}, {"business_status": "OPERATIONAL", "geometry": {"location": {"lat": 40.7282139, "lng": -3.8582334}, "viewport": {"northeast": {"lat": 40.7296647802915, "lng": -3.856917969708498}, "southwest": {"lat": 40.72696681970851, "lng": -3.859615930291503}}}, "icon": "https://maps.gstatic.com/mapfiles/place_api/icons/v1/png_71/civic_building-71.png", "icon_background_color": "#7B9EB0", "icon_mask_base_uri": "https://maps.gstatic.com/mapfiles/place_api/icons/v2/civic-bldg_pinlet", "international_phone_number": "+34 918 53 00 35", "name": "Civil Guard barracks", "opening_hours": {"open_now": false}, "place_id": "ChIJx_wEIyx7QQ0Rpii00cHd690", "plus_code": {"compound_code": "P4HR+7P Manzanares el Real, Spain", "global_code": "8CGRP4HR+7P"}, "rating": 3.7, "reference": "ChIJx_wEIyx7QQ0Rpii00cHd690", "scope": "GOOGLE", "types": ["police", "point_of_interest", "establishment"], "user_ratings_total": 3, "vicinity": "Avenida de Madrid, 24, Manzanares el Real"}]